alf/__init__.py
alf/folders.py
alf/io.py
brainbox/__init__.py
brainbox/misc.py
brainbox/behavior/__init__.py
brainbox/behavior/behavior.py
brainbox/behavior/wheel.py
brainbox/core/__init__.py
brainbox/core/core.py
brainbox/experimental/__init__.py
brainbox/io/__init__.py
brainbox/population/__init__.py
brainbox/processing/__init__.py
brainbox/processing/processing.py
brainbox/simulation/__init__.py
brainbox/singlecell/__init__.py
brainbox/task/__init__.py
ibllib/__init__.py
ibllib/graphic.py
ibllib/plots.py
ibllib/time.py
ibllib/dsp/__init__.py
ibllib/dsp/fourier.py
ibllib/dsp/savitzky_golay.py
ibllib/dsp/smooth.py
ibllib/dsp/utils.py
ibllib/ephys/__init__.py
ibllib/ephys/ephysqc.py
ibllib/io/__init__.py
ibllib/io/ascii.py
ibllib/io/flags.py
ibllib/io/globus.py
ibllib/io/jsonable.py
ibllib/io/npy_header.py
ibllib/io/one.py
ibllib/io/params.py
ibllib/io/raw_data_loaders.py
ibllib/io/spikeglx.py
ibllib/io/extractors/__init__.py
ibllib/io/extractors/biased_trials.py
ibllib/io/extractors/biased_wheel.py
ibllib/io/extractors/ephys_fpga.py
ibllib/io/extractors/ephys_trials.py
ibllib/io/extractors/training_audio.py
ibllib/io/extractors/training_trials.py
ibllib/io/extractors/training_wheel.py
ibllib/misc/__init__.py
ibllib/misc/flatten.py
ibllib/misc/misc.py
ibllib/misc/timing.py
ibllib/misc/version.py
ibllib/pipes/__init__.py
ibllib/pipes/experimental_data.py
ibllib/pipes/extract_session.py
ibllib/pipes/purge_rig_data.py
ibllib/pipes/transfer_rig_data.py
oneibl/__init__.py
oneibl/dataclass.py
oneibl/globus.py
oneibl/one.py
oneibl/params.py
oneibl/registration.py
oneibl/webclient.py
tests/__init__.py
tests/alf/__init__.py
tests/alf/test_alf_io.py
tests/brainbox/__init__.py
tests/brainbox/test_behavior.py
tests/brainbox/test_core.py
tests/brainbox/test_processing.py
tests/ibllib/__init__.py
tests/ibllib/test_dsp.py
tests/ibllib/test_imports.py
tests/ibllib/test_io.py
tests/ibllib/test_misc.py
tests/ibllib/test_pipes.py
tests/ibllib/test_time.py
brainbox_ibl-1.0.0.dist-info/LICENSE
brainbox_ibl-1.0.0.dist-info/METADATA
brainbox_ibl-1.0.0.dist-info/WHEEL
brainbox_ibl-1.0.0.dist-info/top_level.txt
brainbox_ibl-1.0.0.dist-info/RECORD
