Metadata-Version: 2.1
Name: brainbox-ibl
Version: 1.0.0
Summary: International Brain Laboratory data pipeline library
Home-page: https://www.internationalbrainlab.com/
Author: Jai Bhagat
Author-email: jai.bhagat@internationalbrainlab.com
License: MIT
Platform: UNKNOWN
Requires-Python: >=3.6
Requires-Dist: colorlog (>=4.0.2)
Requires-Dist: dataclasses (>=0.6)
Requires-Dist: globus-sdk (>=1.7.1)
Requires-Dist: matplotlib (>=3.0.3)
Requires-Dist: numpy (>=1.16.4)
Requires-Dist: pandas (>=0.24.2)
Requires-Dist: requests (>=2.22.0)
Requires-Dist: scipy (>=1.3.0)
Requires-Dist: seaborn (>=0.9.0)
Requires-Dist: flake8 (>=3.7.8)
